array_nodes.py
compiler.py
enhanced_parser.py
hybrid_parser.py
interpreter.py
lexer.py
main.py
nova.py
nova_cli.py
novalang_auto_main.py
novalang_runtime.py
parser.py
simple_parser.py
stdlib.py
working_demo.py
novalang/__init__.py
novalang/interpreter.py
novalang/lexer.py
novalang/lsp_server.py
novalang/main.py
novalang/nova.py
novalang/package.json
novalang/parser.py
novalang-2.2.5.dist-info/licenses/LICENSE
novalang-backend-clean/.env.example
novalang-backend-clean/array_assign_node.py
novalang-backend-clean/array_nodes.py
novalang-backend-clean/entities.py
novalang-backend-clean/entity_system.py
novalang-backend-clean/for_node.py
novalang-backend-clean/interpreter.py
novalang-backend-clean/lexer.py
novalang-backend-clean/main.py
novalang-backend-clean/novalang-backend.code-workspace
novalang-backend-clean/novalang_database_setup.sql
novalang-backend-clean/parser.py
novalang-backend-clean/requirements.txt
novalang-backend-clean/springboot_backend.nova
novalang-backend-clean/springboot_style.nova
novalang-backend-clean/src/main/novalang/Application.nova
novalang-backend-clean/src/main/novalang/DatabaseCreator.nova
novalang-backend-clean/src/main/novalang/RealDatabaseApp.nova
novalang-backend-clean/src/main/novalang/config/DatabaseConfig.nova
novalang-backend-clean/src/main/novalang/config/MySQLWorkbenchSetup.nova
novalang-backend-clean/src/main/novalang/config/RealMySQLConfig.nova
novalang-backend-clean/src/main/novalang/entity/Order.nova
novalang-backend-clean/src/main/novalang/entity/Product.nova
novalang-backend-clean/src/main/novalang/entity/User.nova
novalang-backend-clean/src/main/novalang/repository/OrderRepository.nova
novalang-backend-clean/src/main/novalang/repository/ProductRepository.nova
novalang-backend-clean/src/main/novalang/repository/UserRepository.nova
novalang-backend-clean/src/main/novalang/service/ProductService.nova
novalang-backend-clean/src/main/novalang/service/UserService.nova
novalang-demo/DemoApp.nova
novalang-demo/nova.json
novalang-demo/novalang_runtime.py
novalang-2.2.5.dist-info/METADATA
novalang-2.2.5.dist-info/WHEEL
novalang-2.2.5.dist-info/entry_points.txt
novalang-2.2.5.dist-info/top_level.txt
novalang-2.2.5.dist-info/RECORD
