Metadata-Version: 2.4
Name: novalang
Version: 2.2.5
Summary: NovaLang - Universal Programming Language with Clean API Templates
Home-page: https://github.com/martinmaboya/novalang
Author: martinmaboya
Author-email: Martin Maboya <martinmaboya@gmail.com>
License: MIT
Project-URL: Homepage, https://github.com/martinmaboya/novalang
Project-URL: Documentation, https://novalang.readthedocs.io/
Project-URL: Repository, https://github.com/martinmaboya/novalang
Project-URL: Bug Reports, https://github.com/martinmaboya/novalang/issues
Project-URL: Changelog, https://github.com/martinmaboya/novalang/blob/master/CHANGELOG.md
Keywords: programming-language,database,sql,nosql,mysql,postgresql,mongodb,redis,elasticsearch,neo4j,cassandra,influxdb,oracle,sqlserver,artificial-intelligence,machine-learning,blockchain,cloud-native,microservices,enterprise,universal-database,orm,jpa,hibernate,vector-database,graph-database,time-series,search-engine,compiler,interpreter
Classifier: Development Status :: 5 - Production/Stable
Classifier: Intended Audience :: Developers
Classifier: Topic :: Software Development :: Interpreters
Classifier: Topic :: Software Development :: Compilers
Classifier: Topic :: Database
Classifier: Topic :: Database :: Database Engines/Servers
Classifier: Topic :: Scientific/Engineering :: Artificial Intelligence
Classifier: Topic :: Software Development :: Libraries :: Application Frameworks
Classifier: License :: OSI Approved :: MIT License
Classifier: Programming Language :: Python :: 3
Classifier: Programming Language :: Python :: 3.8
Classifier: Programming Language :: Python :: 3.9
Classifier: Programming Language :: Python :: 3.10
Classifier: Programming Language :: Python :: 3.11
Classifier: Programming Language :: Python :: 3.12
Classifier: Programming Language :: Python :: 3.13
Classifier: Operating System :: OS Independent
Requires-Python: >=3.8
License-File: LICENSE
Requires-Dist: dataclasses; python_version < "3.7"
Provides-Extra: dev
Requires-Dist: pytest>=6.0; extra == "dev"
Requires-Dist: black>=21.0; extra == "dev"
Requires-Dist: flake8>=3.8; extra == "dev"
Requires-Dist: mypy>=0.800; extra == "dev"
Provides-Extra: database
Requires-Dist: psycopg2-binary>=2.8.0; extra == "database"
Requires-Dist: pymongo>=4.0.0; extra == "database"
Requires-Dist: redis>=4.0.0; extra == "database"
Requires-Dist: elasticsearch>=8.0.0; extra == "database"
Requires-Dist: neo4j>=5.0.0; extra == "database"
Requires-Dist: cassandra-driver>=3.25.0; extra == "database"
Requires-Dist: influxdb-client>=1.30.0; extra == "database"
Provides-Extra: all
Requires-Dist: pytest>=6.0; extra == "all"
Requires-Dist: black>=21.0; extra == "all"
Requires-Dist: flake8>=3.8; extra == "all"
Requires-Dist: mypy>=0.800; extra == "all"
Requires-Dist: psycopg2-binary>=2.8.0; extra == "all"
Requires-Dist: pymongo>=4.0.0; extra == "all"
Requires-Dist: redis>=4.0.0; extra == "all"
Requires-Dist: elasticsearch>=8.0.0; extra == "all"
Requires-Dist: neo4j>=5.0.0; extra == "all"
Requires-Dist: cassandra-driver>=3.25.0; extra == "all"
Requires-Dist: influxdb-client>=1.30.0; extra == "all"
Dynamic: author
Dynamic: home-page
Dynamic: license-file
Dynamic: requires-python
